<TextFileConfiguration>
	<FilePath>practica1/BaseCasos2.txt</FilePath>
	<Delimiters>,</Delimiters>
	<DescriptionClassName>practica1.QuinielaCaso</DescriptionClassName>
	<DescriptionMappings>
		<Map>nombreLocal</Map>
		<Map>resultLocal</Map>
		<Map>resultVisit</Map>
		<Map>nombreVisitante</Map>
		<Map>jornada</Map>
		<Map>temporada</Map>
		<Map>division</Map>
		<Map>posLocal</Map>
		<Map>puntosLocal</Map>
		<Map>golesFavorLocal</Map>
		<Map>golesContraLocal</Map>
		<Map>puntosCasaLocal</Map>
		<Map>puntosFueraLocal</Map>
		<Map>posVis</Map>
		<Map>puntosVis</Map>
		<Map>golesFavorVis</Map>
		<Map>golesContraVis</Map>
		<Map>puntosCasaVis</Map>
		<Map>puntosFueraVis</Map>
		<Map>difPuntos</Map>
		<Map>difPos</Map>
	</DescriptionMappings>
	<SolutionClassName>practica1.QuinielaSolution</SolutionClassName>
	<SolutionMappings>
		<Map>confianza</Map>
		<Map>resultado</Map>
	</SolutionMappings>
</TextFileConfiguration>